Metadata-Version: 2.1
Name: odoo12-addon-sale-commission
Version: 12.0.3.3.3
Summary: Sales commissions
Home-page: https://github.com/OCA/commission
Author: Tecnativa,Odoo Community Association (OCA)
Author-email: support@odoo-community.org
License: AGPL-3
Platform: UNKNOWN
Classifier: Programming Language :: Python
Classifier: Framework :: Odoo
Classifier: Framework :: Odoo :: 12.0
Classifier: License :: OSI Approved :: GNU Affero General Public License v3
Classifier: Development Status :: 6 - Mature
Requires-Python: >=3.5
Requires-Dist: odoo <12.1dev,>=12.0a
